{
    "string":[
        {
            "name":"call_meeting",
            "value":"ཁ་པར་ཚོགས་འདུ།",
            "attr":{
                "priority":"LT"
            }
        },
        {
            "name":"specified_number",
            "value":"དམིགས་འཛུགས་ཨང་གྲངས།",
            "attr":{
                "priority":"LT"
            }
        },
        {
            "name":"cancel",
            "value":"འདོར་བ།",
            "attr":{
                "priority":"LT"
            }
        },
        {
            "name":"is_delete_number",
            "value":"ཨང་གྲངས་འདི་སུབ་བམ།",
            "attr":{
                "priority":"LT"
            }
        },
        {
            "name":"is_delete_all_number",
            "value":"ཨང་གྲངས་ཆ་ཚང་སུབ་བམ།",
            "attr":{
                "priority":"LT"
            }
        },
        {
            "name":"deselect_all",
            "value":"ཡོངས་འདེམས་འདོར་བ།",
            "attr":{
                "priority":"LT"
            }
        },
        {
            "name":"select_all",
            "value":"ཡོངས་འདེམས།",
            "attr":{
                "priority":"LT"
            }
        },
        {
            "name":"unknown",
            "value":"རྒྱུས་མེད།",
            "attr":{
                "priority":"translate"
            }
        },
        {
            "name":"delete",
            "value":"སུབ་པ།",
            "attr":{
                "priority":"LT"
            }
        },
        {
            "name":"automatic_recording_of_calls",
            "value":"ཁ་པར་རང་འགུལ་སྒྲ་ཕབ།",
            "attr":{
                "priority":"LT"
            }
        },
        {
            "name":"unset_recorder",
            "value":"སྒྲིག་འགོད་བྱས་མེད།",
            "attr":{
                "priority":"LT"
            }
        },
        {
            "name":"auto_recording_object",
            "value":"རང་འགུལ་སྒྲ་ཕབ་བྱ་ཡུལ།",
            "attr":{
                "priority":"LT"
            }
        },
        {
            "name":"no_number_specified",
            "value":"ཨང་གྲངས་མི་འདུག",
            "attr":{
                "priority":"LT"
            }
        },
        {
            "name":"automatically_record_call_viewed",
            "value":"ཁ་པར་གཏོང་ཐུབ་རྗེས་རང་འགུལ་ངང་སྒྲ་ཕབ་པར་བྱ། སྒྲ་ཕབ་ཡིག་ཆ་སྒྲ་ཕབ་འཕྲུལ་ཆས་ཀྱི་ཉེར་སྤྱོད་ཁྲོད་ནས་མཐོང་ཐུབ།",
            "attr":{
                "priority":"LT"
            }
        },
        {
            "name":"call_numbers_finish_des",
            "value":"༼ཁ་པར་༽>༼དེ་ལས་མང་བ་༽>༼ཁ་པར་གཏོང་ལེན་གྱི་སྒྲ་ཕབ་༽ནང་དུ་ཉར་ཚགས་བྱས་ཟིན། བརྡབས་ནས་ལྟ་ཞིབ་གནང་རོགས།",
            "attr":{
                "priority":"LT"
            }
        },
        {
            "name":"add_specified_number",
            "value":"དམིགས་འཛུགས་ཨང་གྲངས་སྣོན་པ།",
            "attr":{
                "priority":"LT"
            }
        },
        {
            "name":"all_calls",
            "value":"ཁ་པར་གཏོང་ལེན་ཚང་མ།",
            "attr":{
                "priority":"LT"
            }
        },
        {
            "name":"add",
            "value":"སྣོན་པ།",
            "attr":{
                "priority":"translate"
            }
        },
        {
            "name":"voice_long_press",
            "value":"ཉིས་རྡེབ་བྱས་ནས་མནན་ཚེ་གདམ་ག་དེ་ལས་མང་བ་འཕར་ཐོན་བྱེད།",
            "attr":{
                "priority":"translate"
            }
        }
    ]
}